fd_ufc_scraper/__init__.py
fd_ufc_scraper/config.py
fd_ufc_scraper/fd_ufc_scraper.py
fd_ufc_scraper/fd_ufcscraper.py
fd_ufc_scraper-1.0.0.dist-info/METADATA
fd_ufc_scraper-1.0.0.dist-info/WHEEL
fd_ufc_scraper-1.0.0.dist-info/top_level.txt
fd_ufc_scraper-1.0.0.dist-info/RECORD
