Metadata-Version: 2.4
Name: fd_ufc_scraper
Version: 1.0.0
Summary: A Python package to scrape UFC events and fighter data
Home-page: https://github.com/KushyKernel/UFC
Author: Tife Kusimo
Author-email: tife.kusimo@gmail.com
Classifier: Programming Language :: Python :: 3
Classifier: License :: OSI Approved :: MIT License
Classifier: Operating System :: OS Independent
Requires-Python: >=3.6
Requires-Dist: requests
Requires-Dist: lxml
Requires-Dist: googlesearch-python
Dynamic: author
Dynamic: author-email
Dynamic: classifier
Dynamic: home-page
Dynamic: requires-dist
Dynamic: requires-python
Dynamic: summary
